taskbeacon_mcp/__init__.py
taskbeacon_mcp/main.py
taskbeacon_mcp-0.1.7.dist-info/licenses/LICENSE
taskbeacon_mcp-0.1.7.dist-info/METADATA
taskbeacon_mcp-0.1.7.dist-info/WHEEL
taskbeacon_mcp-0.1.7.dist-info/entry_points.txt
taskbeacon_mcp-0.1.7.dist-info/top_level.txt
taskbeacon_mcp-0.1.7.dist-info/RECORD
