Metadata-Version: 2.4
Name: taskbeacon-mcp
Version: 0.1.7
Summary: A model contexture protocal (MCP) for TaskBeacon
Author-email: Zhipeng Cao <zhipeng30@foxmail.com>
License-Expression: MIT
Project-URL: Homepage, https://github.com/TaskBeacon/taskbeacon-mcp
Project-URL: Repository, https://github.com/TaskBeacon/taskbeacon-mcp
Project-URL: Bug Tracker, https://github.com/TaskBeacon/taskbeacon-mcp/issues
Keywords: taskbeacon,mcp,uv,TaskBeacon
Classifier: Programming Language :: Python :: 3
Classifier: Operating System :: OS Independent
Requires-Python: >=3.10
License-File: LICENSE
Requires-Dist: httpx
Requires-Dist: GitPython
Requires-Dist: mcp[cli]
Requires-Dist: ruamel.yaml
Requires-Dist: edge_tts
Requires-Dist: fuzzywuzz
Dynamic: license-file
